Day5/full_subtractor.v
module full_subtractor(input a, b, Bin, output D, Bout);
assign D = a ^ b ^ Bin;
assign Bout = (~a & b) | (~(a ^ b) & Bin);
endmodule

Day5/full_subtractor_tb.v
module tb_top;
reg a, b, Bin;
wire D, Bout;
full_subtractor fs(a, b, Bin, D, Bout);
initial begin
$dumpfile("waveform.vcd");
$dumpvars(0, tb_top);
$monitor("At time %0t: a=%b b=%b, Bin=%b, difference=%b, borrow=%b",$time,
a,b,Bin,D,Bout);
a = 0; b = 0; Bin = 0; #1;
a = 0; b = 0; Bin = 1; #1;
a = 0; b = 1; Bin = 0; #1;
a = 0; b = 1; Bin = 1; #1;
a = 1; b = 0; Bin = 0; #1;
a = 1; b = 0; Bin = 1; #1;
a = 1; b = 1; Bin = 0; #1;
a = 1; b = 1; Bin = 1;
#3;
$finish();
end
endmodule

Day5/waveform.vcd
$date
	Sun Jul 28 00:51:29 2024
$end
$version
	Icarus Verilog
$end
$timescale
	1s
$end
$scope module tb_top $end
$var wire 1 ! D $end
$var wire 1 " Bout $end
$var reg 1 # Bin $end
$var reg 1 $ a $end
$var reg 1 % b $end
$scope module fs $end
$var wire 1 # Bin $end
$var wire 1 " Bout $end
$var wire 1 ! D $end
$var wire 1 $ a $end
$var wire 1 % b $end
$upscope $end
$upscope $end
$enddefinitions $end
$comment Show the parameter values. $end
$dumpall
$end
#0
$dumpvars
0%
0$
0#
0"
0!
$end
#1
1"
1!
1#
#2
0#
1%
#3
0!
1#
#4
0"
1!
0#
0%
1$
#5
0!
1#
#6
0#
1%
#7
1"
1!
1#
